activity5.v
`include "mips.h" // various defines
/*instruction types locations*/
`define regDst  10
`define jump  9
`define branch  8
`define memRead  7
`define memToReg  6
`define aluOP  5:3 //i need this and the next two after it to fully access aluOP
`define regWrite  2
`define aluSrc  1
`define memWrite  0

module pcRegister(input clock, input  [31:0] next_addr, output reg [31:0] addr);

initial begin
	addr = 32'h00400020;
	end
always @(posedge clock)//negedge would have worked too ? clock usage was not specified
	addr <= next_addr;
endmodule
////////////

module adder(input [31:0] addr, output reg [31:0] out);

always@(addr)
	out <= addr + 4; //I got error for using assign

endmodule
////////////

module memory(input [31:0] addr, output reg [31:0] instruction);

reg [31:0] mem [32'h100000:32'h101000]; // ask why this instead of [3:0]
reg [31:0] word_addr;

initial begin
	$readmemh("add_test.v", mem);
end
always @(addr)
begin
	word_addr = addr >> 2; // ask difference btwn read and word address and need for this >>2
	instruction = mem[word_addr];
end
endmodule
////////////

module control(input [31:0] instruction, output reg [10:0] val);
always@(instruction) begin
	if((instruction[`op] == `SPECIAL) && (instruction[`function] == `ADD)) begin//add
		val = 11'b10000010100;
		$display("Add Instruction");
		end
	else if((instruction[`op] == `SPECIAL) && (instruction[`function] == `SUB)) //sub
		val = 11'b10000110100;
	else if((instruction[`op] == `SPECIAL) && (instruction[`function] == `AND)) //and
		val = 11'b10000000100;
	else if((instruction[`op] == `SPECIAL) && (instruction[`function] == `OR)) //or
		val = 11'b10000001100;
	else if((instruction[`op] == `SPECIAL) && (instruction[`function] == `SLT)) //slt
		val = 11'b10000111100;
	else if(instruction[`op] == `ADDI)//addi
		val = 11'b00000010110;
	else if(instruction[`op] == `ORI)//ori
		val = 11'b00000001110;
	else if(instruction[`op] == `LW)//lw
		val = 11'b00011010110;
	else if(instruction[`op] == `SW)//sw
		val = 11'b00000010011;
	else if(instruction[`op] == `BEQ)//beq
		val = 11'b00100110000;
	else if(instruction[`op] == `BNE)//bne
		val = 11'b00100110000;
	else if(instruction[`op] == `J) begin//j
		val = 11'b01000000000;
		$display("Jump Instruction");
		$display("control bits - %x", val);
		end
	else if(instruction[`op] == `JR)//jr
		val = 11'b01000000000;
	else if(instruction[`op] == `JAL)//jal
		val = 11'b01000000100;
	else begin
		$display("instruction not supported, instruction - %x", instruction);
		$display("instruction opcode - %x", instruction[`op]);	
		val = 11'b0;	
	end
	end
endmodule
////////////

module shift(input [31:0] addr, input [31:0] instruction, output reg [31:0] jumpAddr);
reg [31:0] next_addr;
always@(instruction)begin
	next_addr = addr + 4;
	jumpAddr = {next_addr[31:28], instruction[25:0] << 2};
end
endmodule
////////////

module mux_Jump(input val, input [31:0] jumpAddr, input [31:0] addrFromAdder, output reg [31:0] next_addr);
always@(*) begin
	if(val == 1)
		next_addr = jumpAddr;
	else
		next_addr = addrFromAdder;
end
endmodule
////////////

module muxForRegisters(input [31:0] instruction, input RegDst, output reg [4:0] writeReg);
always @(*) begin
	if(RegDst == 1)
		writeReg = instruction[15:11]; //instruction[15-11]
	else
		writeReg = instruction[20:16]; //instruction[20-16]
	end
endmodule

module registers(input [4:0] rd1, input [4:0] rd2, input[4:0] writeRegister, input [31:0] rr, input write, output reg [31:0] data1, output reg [31:0] data2, output reg [31:0] v0, output reg [31:0] a0);
reg [31:0] register [31:0];

always @(*) begin
v0 = register[`v0];
$display("registers");
a0 = register[`a0];
data1 = register[rd1];
data2 = register[rd2];
if(write)
	register[writeRegister] = rr;
end
endmodule
/////////////////////////////////////////////////

module signExtend(input [15:0] instruc, output reg [31:0] signExtendReadData);
	always @(*) begin
		signExtendReadData = {{16{instruc[15]}},instruc[15:0]};
		end
endmodule


module muxForALU(input aluSrc, input [31:0] readData2, input [31:0] signExtendReadData, output reg [31:0] muxResult);
always @(*) begin
if(aluSrc == 0)
	muxResult = readData2;
else
	muxResult = signExtendReadData;
end
endmodule

module alu(input [2:0] aluOp,input [31:0] readData, input [31:0] readData2, output reg [31:0] aluResult);
// aluOp comes from the control signal
always@(*) begin
	if(aluOp == 3'b010)//add
		aluResult = readData + readData2;
	else if(aluOp == 3'b110)//subtract
		aluResult = readData - readData2;
	else if(aluOp == 3'b001)//or
		aluResult = readData | readData2;
	else if(aluOp == 3'b000)//and
		aluResult = readData & readData2;
	//else if(aluOp == 3'b111)//slt
		//aluResult = 
	end
endmodule
/////////////////////////

module syscall(input[31:0] instruction, input [31:0] v0, input [31:0] a0);
always@(*) begin
if(instruction == 32'h0000000C) begin
	if(v0 == 1)
		$display("a0 - %x",a0);
	else if(v0 == 10)
		$finish;
end
end
endmodule

//module dataMemory(input [31:0] address, input [31:0] writeData, input [31:0] readData, input memRead, input memWrite);

//endmodule
////////////////////

module testbench;
reg clock = 0;
wire [31:0] current_addr;
wire [31:0] add_addr;
wire [31:0] jump_addr;
wire [10:0] val;
wire [31:0] next_addr;
wire [31:0] next_addr2;
wire [31:0] instruction;
wire [4:0] writeReg;
wire [31:0] rr; //setting to aluResult for first test but should actually come from mux of dataMem and aluResult
wire [31:0] aluResult;
wire [31:0] readData1;
wire [31:0] readData2;
wire [31:0] a0;
wire [31:0] v0;
wire [31:0] signExtendData;
wire [31:0] muxAluResult;

adder add(current_addr, add_addr);
memory mem(current_addr, instruction);
control con(instruction, val);
shift shi(current_addr, instruction, jump_addr);
mux_Jump m(val[`jump], jump_addr, add_addr, next_addr);//checks jump
pcRegister pc(clock, next_addr, current_addr);
muxForRegisters muxForR(instruction, val[`regDst], writeReg);
//change aluResult to rr
registers regis(instruction[25:21],instruction[20:16],writeReg,aluResult, val[`regWrite], readData1, readData2, v0, a0);
syscall sys(instruction, v0, a0);
signExtend sE(instruction[15:0], signExtendData);
muxForALU muxForA(val[`aluSrc], readData2, signExtendData, muxAluResult);
alu al(val[`aluOP], readData1, muxAluResult, aluResult);
initial
begin
    $dumpfile("test.vcd");
    $dumpvars(0,testbench);	
    //$monitor("instruction = %08x, val - control bits = %08x", instruction, val);
end

always
  begin                     // inline clock generator
    #10; clock = ~clock;
    if(instruction == 32'h0000000C) begin
	$display("here");
	$display("v0 - %x",v0);
	$display("a0 - %x",a0);
	if(v0 == 1)
		$display("a0 - %x",a0);
	else if(v0 == 10)
		$finish;
	end
    if(instruction == 0)
	$finish;
  end

endmodule

test.vcd
$date
	Fri Sep  8 12:07:49 2017
$end
$version
	Icarus Verilog
$end
$timescale
	1s
$end
$scope module testbench $end
$var wire 5 ! writeReg [4:0] $end
$var wire 11 " val [10:0] $end
$var wire 32 # v0 [31:0] $end
$var wire 32 $ signExtendData [31:0] $end
$var wire 32 % readData2 [31:0] $end
$var wire 32 & readData1 [31:0] $end
$var wire 32 ' next_addr [31:0] $end
$var wire 32 ( muxAluResult [31:0] $end
$var wire 32 ) jump_addr [31:0] $end
$var wire 32 * instruction [31:0] $end
$var wire 32 + current_addr [31:0] $end
$var wire 32 , aluResult [31:0] $end
$var wire 32 - add_addr [31:0] $end
$var wire 32 . a0 [31:0] $end
$var reg 1 / clock $end
$scope module add $end
$var wire 32 0 addr [31:0] $end
$var reg 32 1 out [31:0] $end
$upscope $end
$scope module al $end
$var wire 3 2 aluOp [2:0] $end
$var wire 32 3 readData2 [31:0] $end
$var wire 32 4 readData [31:0] $end
$var reg 32 5 aluResult [31:0] $end
$upscope $end
$scope module con $end
$var wire 32 6 instruction [31:0] $end
$var reg 11 7 val [10:0] $end
$upscope $end
$scope module m $end
$var wire 32 8 addrFromAdder [31:0] $end
$var wire 1 9 val $end
$var wire 32 : jumpAddr [31:0] $end
$var reg 32 ; next_addr [31:0] $end
$upscope $end
$scope module mem $end
$var wire 32 < addr [31:0] $end
$var reg 32 = instruction [31:0] $end
$var reg 32 > word_addr [31:0] $end
$upscope $end
$scope module muxForA $end
$var wire 1 ? aluSrc $end
$var wire 32 @ signExtendReadData [31:0] $end
$var wire 32 A readData2 [31:0] $end
$var reg 32 B muxResult [31:0] $end
$upscope $end
$scope module muxForR $end
$var wire 1 C RegDst $end
$var wire 32 D instruction [31:0] $end
$var reg 5 E writeReg [4:0] $end
$upscope $end
$scope module pc $end
$var wire 1 / clock $end
$var wire 32 F next_addr [31:0] $end
$var reg 32 G addr [31:0] $end
$upscope $end
$scope module regis $end
$var wire 5 H rd1 [4:0] $end
$var wire 5 I rd2 [4:0] $end
$var wire 32 J rr [31:0] $end
$var wire 1 K write $end
$var wire 5 L writeRegister [4:0] $end
$var reg 32 M a0 [31:0] $end
$var reg 32 N data1 [31:0] $end
$var reg 32 O data2 [31:0] $end
$var reg 32 P v0 [31:0] $end
$upscope $end
$scope module sE $end
$var wire 16 Q instruc [15:0] $end
$var reg 32 R signExtendReadData [31:0] $end
$upscope $end
$scope module shi $end
$var wire 32 S addr [31:0] $end
$var wire 32 T instruction [31:0] $end
$var reg 32 U jumpAddr [31:0] $end
$var reg 32 V next_addr [31:0] $end
$upscope $end
$scope module sys $end
$var wire 32 W a0 [31:0] $end
$var wire 32 X instruction [31:0] $end
$var wire 32 Y v0 [31:0] $end
$upscope $end
$upscope $end
$enddefinitions $end
#0
$dumpvars
bx Y
b100100000010000000000000000001 X
bx W
b10000000000000000100100 V
b1000000000000000000100 U
b100100000010000000000000000001 T
b10000000000000000100000 S
b1 R
b1 Q
bx P
bx O
bx N
bx M
b1000 L
0K
bx J
b1000 I
b0 H
b10000000000000000100000 G
b10000000000000000100100 F
b1000 E
b100100000010000000000000000001 D
0C
bx B
bx A
b1 @
0?
b100000000000000001000 >
b100100000010000000000000000001 =
b10000000000000000100000 <
b10000000000000000100100 ;
b1000000000000000000100 :
09
b10000000000000000100100 8
b0 7
b100100000010000000000000000001 6
bx 5
bx 4
bx 3
b0 2
b10000000000000000100100 1
b10000000000000000100000 0
0/
bx .
b10000000000000000100100 -
bx ,
b10000000000000000100000 +
b100100000010000000000000000001 *
b1000000000000000000100 )
bx (
b10000000000000000100100 '
bx &
bx %
b1 $
bx #
b0 "
b1000 !
$end
#10
b10000000000000000101000 '
b10000000000000000101000 ;
b10000000000000000101000 F
b10000000000000000101000 -
b10000000000000000101000 1
b10000000000000000101000 8
b10 $
b10 @
b10 R
b10 Q
b1001 I
b1001000000000000001000 )
b1001000000000000001000 :
b1001000000000000001000 U
b10000000000000000101000 V
b1001 !
b1001 E
b1001 L
b100100000010010000000000000010 *
b100100000010010000000000000010 6
b100100000010010000000000000010 =
b100100000010010000000000000010 D
b100100000010010000000000000010 T
b100100000010010000000000000010 X
b100000000000000001001 >
b10000000000000000100100 +
b10000000000000000100100 0
b10000000000000000100100 <
b10000000000000000100100 G
b10000000000000000100100 S
1/
#20
0/
#30
b10000000000000000101100 '
b10000000000000000101100 ;
b10000000000000000101100 F
b10000000000000000101100 -
b10000000000000000101100 1
b10000000000000000101100 8
b1 $
b1 @
b1 R
b1 Q
b10 I
b10000000000000000100 )
b10000000000000000100 :
b10000000000000000100 U
b10000000000000000101100 V
b10 !
b10 E
b10 L
b100100000000100000000000000001 *
b100100000000100000000000000001 6
b100100000000100000000000000001 =
b100100000000100000000000000001 D
b100100000000100000000000000001 T
b100100000000100000000000000001 X
b100000000000000001010 >
b10000000000000000101000 +
b10000000000000000101000 0
b10000000000000000101000 <
b10000000000000000101000 G
b10000000000000000101000 S
1/
#40
0/
#50
b10000000000000000110000 '
b10000000000000000110000 ;
b10000000000000000110000 F
b10000000000000000110000 -
b10000000000000000110000 1
b10000000000000000110000 8
b10000000100000 $
b10000000100000 @
b10000000100000 R
b10 2
1K
1C
b10000000100000 Q
b1000 I
b1001 H
b10000010100 "
b10000010100 7
b101000001000000010000000 )
b101000001000000010000000 :
b101000001000000010000000 U
b10000000000000000110000 V
b100 !
b100 E
b100 L
b1001010000010000000100000 *
b1001010000010000000100000 6
b1001010000010000000100000 =
b1001010000010000000100000 D
b1001010000010000000100000 T
b1001010000010000000100000 X
b100000000000000001011 >
b10000000000000000101100 +
b10000000000000000101100 0
b10000000000000000101100 <
b10000000000000000101100 G
b10000000000000000101100 S
1/
#60
0/
#70
b10000000000000000110100 '
b10000000000000000110100 ;
b10000000000000000110100 F
b10000000000000000110100 -
b10000000000000000110100 1
b10000000000000000110100 8
b1100 $
b1100 @
b1100 R
b0 2
0K
0C
b1100 Q
b0 I
b0 H
b110000 )
b110000 :
b110000 U
b10000000000000000110100 V
b0 "
b0 7
b0 !
b0 E
b0 L
b1100 *
b1100 6
b1100 =
b1100 D
b1100 T
b1100 X
b100000000000000001100 >
b10000000000000000110000 +
b10000000000000000110000 0
b10000000000000000110000 <
b10000000000000000110000 G
b10000000000000000110000 S
1/
#80
0/
#90
b10000000000000000111000 '
b10000000000000000111000 ;
b10000000000000000111000 F
b10000000000000000111000 -
b10000000000000000111000 1
b10000000000000000111000 8
b1010 $
b1010 @
b1010 R
b1010 Q
b10 I
b10000000000000101000 )
b10000000000000101000 :
b10000000000000101000 U
b10000000000000000111000 V
b10 !
b10 E
b10 L
b100100000000100000000000001010 *
b100100000000100000000000001010 6
b100100000000100000000000001010 =
b100100000000100000000000001010 D
b100100000000100000000000001010 T
b100100000000100000000000001010 X
b100000000000000001101 >
b10000000000000000110100 +
b10000000000000000110100 0
b10000000000000000110100 <
b10000000000000000110100 G
b10000000000000000110100 S
1/
#100
0/
#110
b10000000000000000111100 '
b10000000000000000111100 ;
b10000000000000000111100 F
b10000000000000000111100 -
b10000000000000000111100 1
b10000000000000000111100 8
b1100 $
b1100 @
b1100 R
b1100 Q
b0 I
b110000 )
b110000 :
b110000 U
b10000000000000000111100 V
b0 !
b0 E
b0 L
b1100 *
b1100 6
b1100 =
b1100 D
b1100 T
b1100 X
b100000000000000001110 >
b10000000000000000111000 +
b10000000000000000111000 0
b10000000000000000111000 <
b10000000000000000111000 G
b10000000000000000111000 S
1/
#120
0/
#130
b10000000000000001000000 '
b10000000000000001000000 ;
b10000000000000001000000 F
b10000000000000001000000 -
b10000000000000001000000 1
b10000000000000001000000 8
b0 $
b0 @
b0 R
b0 Q
b0 )
b0 :
b0 U
b10000000000000001000000 V
b0 *
b0 6
b0 =
b0 D
b0 T
b0 X
b100000000000000001111 >
b10000000000000000111100 +
b10000000000000000111100 0
b10000000000000000111100 <
b10000000000000000111100 G
b10000000000000000111100 S
1/
